pyghost/__init__.py
pyghost/client.py
pyghost/enums.py
pyghost/exceptions.py
pyghost/images.py
pyghost/members.py
pyghost/newsletters.py
pyghost/offers.py
pyghost/pages.py
pyghost/posts.py
pyghost/py.typed
pyghost/themes.py
pyghost/tiers.py
pyghost/users.py
pyghost/webhooks.py
pyghost-1.0.3.dist-info/licenses/LICENSE
pyghost-1.0.3.dist-info/METADATA
pyghost-1.0.3.dist-info/WHEEL
pyghost-1.0.3.dist-info/top_level.txt
pyghost-1.0.3.dist-info/RECORD
