Metadata-Version: 2.4
Name: pyghost
Version: 1.0.3
Summary: A modern, comprehensive Python wrapper for Ghost Admin API with full CRUD support
Home-page: https://github.com/adamfils/pyghost
Author: PyGhost Contributors
Author-email: PyGhost Contributors <pyghost@example.com>
License: MIT
Project-URL: Homepage, https://github.com/adamfils/pyghost
Project-URL: Documentation, https://github.com/adamfils/pyghost#readme
Project-URL: Repository, https://github.com/adamfils/pyghost
Project-URL: Bug Reports, https://github.com/adamfils/pyghost/issues
Project-URL: Changelog, https://github.com/adamfils/pyghost/releases
Keywords: ghost,cms,api,blog,publishing,content-management,webhooks,themes,members,newsletters
Classifier: Development Status :: 5 - Production/Stable
Classifier: Intended Audience :: Developers
Classifier: License :: OSI Approved :: MIT License
Classifier: Operating System :: OS Independent
Classifier: Programming Language :: Python :: 3
Classifier: Programming Language :: Python :: 3.8
Classifier: Programming Language :: Python :: 3.9
Classifier: Programming Language :: Python :: 3.10
Classifier: Programming Language :: Python :: 3.11
Classifier: Programming Language :: Python :: 3.12
Classifier: Topic :: Software Development :: Libraries :: Python Modules
Classifier: Topic :: Internet :: WWW/HTTP :: Dynamic Content :: Content Management System
Classifier: Topic :: Internet :: WWW/HTTP :: Dynamic Content :: News/Diary
Classifier: Topic :: Communications :: Email :: Mailing List Servers
Classifier: Topic :: Text Processing :: Markup :: HTML
Requires-Python: >=3.8
License-File: LICENSE
Requires-Dist: requests>=2.25.0
Requires-Dist: PyJWT>=2.4.0
Provides-Extra: dev
Requires-Dist: pytest>=6.0; extra == "dev"
Requires-Dist: pytest-cov>=2.0; extra == "dev"
Requires-Dist: flake8>=3.8.0; extra == "dev"
Requires-Dist: black>=21.0.0; extra == "dev"
Requires-Dist: mypy>=0.800; extra == "dev"
Dynamic: author
Dynamic: home-page
Dynamic: license-file
Dynamic: requires-python
